{
  "$schema": "https://developer.microsoft.com/json-schemas/fabric/item/report/definition/visualContainer/2.2.0/schema.json",
  "name": "b9a92c5ce860c09d7a74",
  "position": {
    "x": 56.693349327550813,
    "y": 324.09698032249884,
    "z": 7000,
    "height": 83.150245680407863,
    "width": 283.46674663775406,
    "tabOrder": 7000
  },
  "visual": {
    "visualType": "slicer",
    "query": {
      "queryState": {
        "Values": {
          "projections": [
            {
              "field": {
                "Column": {
                  "Expression": {
                    "SourceRef": {
                      "Entity": "category_dim"
                    }
                  },
                  "Property": "category"
                }
              },
              "queryRef": "category_dim.category",
              "nativeQueryRef": "category",
              "active": true
            }
          ]
        }
      }
    },
    "objects": {
      "data": [
        {
          "properties": {
            "mode": {
              "expr": {
                "Literal": {
                  "Value": "'Dropdown'"
                }
              }
            }
          }
        }
      ],
      "selection": [
        {
          "properties": {
            "selectAllCheckboxEnabled": {
              "expr": {
                "Literal": {
                  "Value": "true"
                }
              }
            }
          }
        }
      ],
      "general": [
        {
          "properties": {}
        }
      ],
      "header": [
        {
          "properties": {
            "show": {
              "expr": {
                "Literal": {
                  "Value": "true"
                }
              }
            },
            "text": {
              "expr": {
                "Literal": {
                  "Value": "'Budget Subcategory'"
                }
              }
            }
          }
        }
      ]
    },
    "visualContainerObjects": {
      "title": [
        {
          "properties": {
            "show": {
              "expr": {
                "Literal": {
                  "Value": "false"
                }
              }
            }
          }
        }
      ]
    },
    "drillFilterOtherVisuals": true
  },
  "filterConfig": {
    "filters": [
      {
        "name": "e021a0ffaa72c9388099",
        "field": {
          "Column": {
            "Expression": {
              "SourceRef": {
                "Entity": "category_dim"
              }
            },
            "Property": "category"
          }
        },
        "type": "Categorical"
      }
    ]
  }
}